django_bunny/__init__.py
django_bunny/storage.py
django_bunny-1.1.6.dist-info/LICENSE
django_bunny-1.1.6.dist-info/METADATA
django_bunny-1.1.6.dist-info/WHEEL
django_bunny-1.1.6.dist-info/RECORD
