Metadata-Version: 2.1
Name: django-bunny
Version: 1.1.6
Summary: A django storage for bunny.net
Home-page: https://github.com/Nekidev/django-bunny/
License: MIT
Keywords: django,bunny,cdn,storage,django-storage
Author: Neki
Author-email: neki@nekidev.com
Maintainer: Neki
Maintainer-email: neki@nekidev.com
Requires-Python: >=3.7,<4.0
Classifier: License :: OSI Approved :: MIT License
Classifier: Programming Language :: Python :: 3
Classifier: Programming Language :: Python :: 3.7
Classifier: Programming Language :: Python :: 3.8
Classifier: Programming Language :: Python :: 3.9
Classifier: Programming Language :: Python :: 3.10
Classifier: Programming Language :: Python :: 3.11
Requires-Dist: Django (>=3.0.0)
Requires-Dist: python-dateutil (>=2.8.2,<3.0.0)
Requires-Dist: requests (>=2.30.0,<3.0.0)
Project-URL: Documentation, https://github.com/Nekidev/django-bunny/tree/main/README.md
Project-URL: Repository, https://github.com/Nekidev/django-bunny/
